dbs_fields/__init__.py
dbs_fields/utils.py
dbs_fields/templates/.DS_Store
dbs_fields/templates/bootstrap3/field.html
dbs_fields/templates/bootstrap3/help_text_and_errors.html
dbs_fields/templates/bootstrap4/.DS_Store
dbs_fields/templates/bootstrap4/custom_field.html
dbs_fields/templates/bootstrap4/field.html
dbs_fields/templates/bootstrap4/general.html
dbs_fields/templates/bootstrap4/help_text_and_errors.html
dbs_fields/templatetags/__init__.py
dbs_fields/templatetags/dbs_tags.py
django_bootstrap_fields-0.1.5.dist-info/LICENSE
django_bootstrap_fields-0.1.5.dist-info/METADATA
django_bootstrap_fields-0.1.5.dist-info/WHEEL
django_bootstrap_fields-0.1.5.dist-info/top_level.txt
django_bootstrap_fields-0.1.5.dist-info/RECORD
