Metadata-Version: 2.1
Name: django-bootstrap-fields
Version: 0.1.5
Summary: render Django form fields with complete Bootstrap HTML markup
Home-page: https://github.com/mtokoly/django-bootstrap-fields
Author: Matthew Tokoly
Author-email: tokoly@gmail.com
License: MIT
Keywords: fields,forms,bootstrap,django
Platform: UNKNOWN
Classifier: Environment :: Web Environment
Classifier: Framework :: Django
Classifier: License :: OSI Approved :: MIT License
Classifier: Programming Language :: JavaScript
Classifier: Programming Language :: Python :: 2.7
Classifier: Programming Language :: Python :: 3.3
Classifier: Programming Language :: Python :: 3.4
Classifier: Programming Language :: Python :: 3.5
Classifier: Programming Language :: Python :: 3.6
Classifier: Topic :: Internet :: WWW/HTTP
Classifier: Topic :: Internet :: WWW/HTTP :: Dynamic Content
Classifier: Topic :: Software Development :: Libraries :: Python Modules
